bellek.v
module bellek(input clk_i,           // Clock girdisi
              input wen_i,           // Yazma yetkilendirme girdisi
              input [31:0] adres_i,   // Okunacak veya yazılacak verinin adresi
              input [31:0] veri_i,   // Belleğe yazılacak veri
              output [31:0] veri_o); // Bellekten okunan veri
    
    // 512x32 bit = 16384 bit = 2048 bayt = 2 kibibayt (2 KiB)
    reg [31:0] mem [511:0];
    
    // program.mem okunup mem içerisine aktarıldı
    initial begin
        $readmemh("program.mem", mem);
    end

    // Clock'tan bağımsız asenkron okuma yapıldı
    assign veri_o = mem[adres_i[10:2]]; // Adresin en anlamsız 2 bitini kullanmadık ve 512 bit boyutunu adresleyebilecek şekilde kısalttık  adres_i[31:2]
    
    
    // Clock'la senkron olan yazma işlemi
    always @(posedge clk_i) begin
        if (wen_i) begin // Yazma yetkilendirilmesi yapıldıysa
            mem[adres_i[10:2]] <= veri_i; // Belleğe veri yazıldı ve 512 bit boyutunu adresleyebilecek şekilde kısalttık   adres_i[31:2]
        end
    end
    
endmodule

kontrolcu.v
module kontrolcu(input [31:0] buyruk_i,                   // Boru hattı kaydedicisinden gelen buyruk
                 output regfile_wen_o,                    // Yazma yetkilendirme çıktısı
                 output [2:0] sabit_genisletici_secimi_o, // İvedi genişletici format seçimi çıkışı
                 output amb_secim_o,                      // AMB ikinci işlenen ifade sabit mi rs2 mi sinyali
                 output reg [3:0] amb_fonksiyon_o);       // AMB fonksiyon seçim sinyali


// Buyruğun bölümleri ayıklanıyor
wire [6:0] opcode = buyruk_i[6:0];
wire [2:0] funct3 = buyruk_i[14:12];
wire [6:0] funct7 = buyruk_i[31:25];

wire [1:0] amb_cozucu;

reg [6:0] control_sinyalleri;
assign {regfile_wen_o, sabit_genisletici_secimi_o, amb_secim_o, amb_cozucu} = control_sinyalleri;

always @(*) begin
    case (opcode)
        7'b0110011  : control_sinyalleri = 7'b1_xxx_0_11; // R-type buyruk
        7'b0010011  : control_sinyalleri = 7'b1_000_1_11; // I-type buyruk
        7'b0000000  : control_sinyalleri = 7'b0_000_0_00; // Sıfırlama durumu
        default     : control_sinyalleri = 7'bx_xxx_x_xx; // Geçersiz buyruk
    endcase
end

// Aritmetik Mantık Biriminde Yapılacak işlemler belirleniyor
always @(*) begin
    case (amb_cozucu)
        2'b11    : // R-type veya I-type
        case (funct3)
            3'b000   : // add-addi veya sub buyruğu
            // Buyruk R-type ise ve funct7 değeri 0x20 ise çıkarma işlemi yapılacaktır
            if (opcode[5] & funct7[5]) begin
                amb_fonksiyon_o = 4'b0001; // sub
                end else begin
                    amb_fonksiyon_o = 4'b0000; // add, addi
                end
                3'b100   : amb_fonksiyon_o = 4'b0011; // xor, xori
                3'b110   : amb_fonksiyon_o = 4'b0100; // or, ori
                3'b111   : amb_fonksiyon_o = 4'b0010; // and, andi
                default  : amb_fonksiyon_o = 4'b0000;
        endcase
        default  : amb_fonksiyon_o = 4'b0000; // Varsayılan işlemi toplama olarak belirledik.
    endcase
end

endmodule

geri_yazma.v
module geri_yazma(input [31:0] amb_cikis_i, // Aritmetik Mantık Biriminin çıkış sinyali alındı
                  output [31:0] sonuc_o);   // alınan sinyal yazdırıldı
assign sonuc_o = amb_cikis_i;
endmodule

src/amb.v
module amb(input amb_secim_i,                // Aritmetik işlemler için 2. ifade rs2 mi yoksa bir sabit(ivedi) değer mi
           input [3:0] amb_fonksiyon_i,      // İşlem seçim sinyali
           input [31:0] reg_a_i,             // rs1 değeri
           input [31:0] reg_b_i,             // rs2 değeri
           input [31:0] sabit_genisletici_i, // imm değeri
           output reg [31:0] amb_cikis_o);   // sonuç değeri
    
    
    // İşlenen buyruk sabit içerse de içermese de ilk ifade her zaman bir register
    wire signed [31:0] amb_a = reg_a_i;
    
    // Seçim sinyali ile MUX yapıldı, sinyale göre ikinci ifade sabit veya rs2 olarak seçildi
    wire signed [31:0] amb_b = amb_secim_i ? sabit_genisletici_i : reg_b_i;
    
    always @(*) begin
        case (amb_fonksiyon_i)
            4'b0000  : amb_cikis_o = amb_a + amb_b;  // Toplama
            4'b0001  : amb_cikis_o = amb_a - amb_b;  // Çıkarma
            4'b0010  : amb_cikis_o = amb_a & amb_b;  // VE
            4'b0011  : amb_cikis_o = amb_a ^ amb_b;  // XOR
            4'b0100  : amb_cikis_o = amb_a | amb_b;  // VEYA
            default  : amb_cikis_o = 32'bx;          // Geçersiz alu_fun_i sinyali
        endcase
    end
    
endmodule

src/boru_hatti/cozucu.v
module cozucu(input clk_i,                            // Clock girdisi
              input regfile_wen_i,                    // Yazma yetkilendirme girdisi
              input [2:0] sabit_genisletici_secimi_i, // İvedi genişletici format seçimi
              input [31:0] buyruk_i,                  // Boru hattı kaydedicisinden gelen buyruk
              input [31:0] sonuc_i,                   // Hedef kaydedicisine (rd) yazılacak değer
              output [31:0] reg_a_o,                  // Birinci kaynak kaydedicisinin (rs1) değeri
              output [31:0] reg_b_o,                  // İkinci kaynak kaydedicisinin (rs2) değeri
              output reg [31:0] sabit_genisletici_o); // İvedi genişleticinin çıkışı
    
    // 32 bit genişliğinde 32 adet kaydedici içeren kaydedici dosyası
    reg [31:0] reg_dosyasi [31:0];
    
    // Buyruk girdisini ayıklama
    wire [4:0] reg_a_adres     = buyruk_i[19:15]; // rs1'in adresi
    wire [4:0] reg_b_adres     = buyruk_i[24:20]; // rs2'nin adresi
    wire [4:0] hedef_reg_adres = buyruk_i[11:7]; // rd'nin adresi
    
    // rs1 ve rs2'nin değerleri kaydedici dosyadan okundu
    // Eğer adresleri 0 noktasını gösteriyorsa okunan değer 0 olarak kabul edildi
    // Esasında 0 adresi farklı değerler içerebilir ama RISC mimarisinde nop buyruğu için
    // Bu adres her zaman 0'a sahipmiş gibi davranılır
    assign reg_a_o = (reg_a_adres == 5'b0) ? 32'b0 : reg_dosyasi[reg_a_adres];
    assign reg_b_o = (reg_b_adres == 5'b0) ? 32'b0 : reg_dosyasi[reg_b_adres];
    
    // Kaydedici dosyasına yazıldı
    always @(posedge clk_i) begin
        if (regfile_wen_i) begin
            reg_dosyasi[hedef_reg_adres] <= sonuc_i;
        end
    end
    
    
    // Sabit(ivedi) genişletici
    // "addi" buyruğu sadece sayının 12 bit'lik kısmını işleyebiliyor
    // Daha sonra "li" buyruğu ile sayının geri kalan bitleri iletiliyor
    // Sadece "addi" buyruğu içeren durum için 12 bit'lik sayı 32 bit'e genişletildi
    always @(*) begin
        case (sabit_genisletici_secimi_i)
            // 12 bitlik sayı 32 bit'e çevrildi
            // Bu yapılırken kalan kısımlar 0 ile doldurulmak yerine 12 bitlik sayının imza biti ile dolduruldu
            // Bu sayede verinin işareti(pozitif/negatif) kaybolmamış oldu
            3'b000   : sabit_genisletici_o = {{20{buyruk_i[31]}}, buyruk_i[31:20]};
            default  : sabit_genisletici_o = 32'b0;
        endcase
    end
    
endmodule

boru_hatti/gc_kaydedici.v
module gc_kaydedici(input clk_i,                   // Clock girdisi
                   input rst_i,                   // Reset sinyali girdisi
                   input [31:0] buyruk_g_i,       // Bellekten gelen buyruk sinyali
                   output reg [31:0] buyruk_c_o); // Boru hattı çözücüsüne giden sinyaş
    
    // Clock ve Reset sinyali pozitif kenarı ile senkron
    always @(posedge clk_i, posedge rst_i) begin
        if (rst_i) begin
            buyruk_c_o <= 32'b0; // Çözücü sinyali sıfırlandı
        end
        else begin
            buyruk_c_o <= buyruk_g_i; // Bellekten gelen buyruk sinyali çözücüye aktarıldı
        end
    end
endmodule

boru_hatti/getir.v
module getir(input clk_i,             // Clock girdisi
             input rst_i,             // Sıfırlama sinyali girdisi
             output reg [31:0] pc_o); // Program sayacı
    
    // Clock ve Reset sinyali pozitif kenarı ile senkron
    always @(posedge clk_i, posedge rst_i) begin // Asenkron Reset sinyali daha iyi olabilir mi??
        if (rst_i) begin // Reset sinyali alındıysa
            pc_o <= 32'b0; // Program sayacını sıfırla
        end
        else begin
            pc_o <= pc_o + 4; // Reset sinyali yoksa clock sinyali ile program sayacını 4 arttır
        end
    end
    
endmodule

kutu.v
module kutu(input clk_i,                    // Clock girdisi
            input rst_i,                    // Reset sinyali girdisi
            input [31:0] buyruk_i,          // Bellekten gelen buyruk
            output [31:0] buyruk_adres_o); // Belleğe giden buyruk adresi
    
    getir getir1(.clk_i(clk_i),
    .rst_i(rst_i),
    .pc_o(buyruk_adres_o));
    
    // Boru hattı kaydedicisi bağlantıları
    wire [31:0] getir_2_cozucu_buyruk;
    gc_kaydedici gc_kaydedici1(
    .clk_i(clk_i),
    .rst_i(rst_i),
    .buyruk_g_i(buyruk_i),
    .buyruk_c_o(getir_2_cozucu_buyruk)
    );
    
    // Çözücü modülü bağlantıları
    wire c2d_regfile_wen;
    wire [2:0] c2d_imm_ext_sel;
    wire [31:0] w2d_result;
    wire [31:0] d2a_reg_a;
    wire [31:0] d2a_reg_b;
    wire [31:0] d2a_imm_ext;
    
    cozucu cozucu1(
    .clk_i(clk_i),
    .regfile_wen_i(c2d_regfile_wen),
    .sabit_genisletici_secimi_i(c2d_imm_ext_sel),
    .buyruk_i(getir_2_cozucu_buyruk),
    .sonuc_i(w2d_result),
    .reg_a_o(d2a_reg_a),
    .reg_b_o(d2a_reg_b),
    .sabit_genisletici_o(d2a_imm_ext)
    );
    
    // Aritmetik Mantık Birimi bağlantıları
    wire c2a_alu_sel;
    wire [3:0] c2a_alu_fun;
    wire [31:0] a2w_alu_out;
    
    amb amb1 (
    .amb_secim_i(c2a_alu_sel),
    .amb_fonksiyon_i(c2a_alu_fun),
    .reg_a_i(d2a_reg_a),
    .reg_b_i(d2a_reg_b),
    .sabit_genisletici_i(d2a_imm_ext),
    .amb_cikis_o(a2w_alu_out)
    );
    
    geri_yazma geri_yazma1 (
    .amb_cikis_i(a2w_alu_out),
    .sonuc_o(w2d_result)
    );
    
    kontrolcu kontrolcu1 (
    .buyruk_i(getir_2_cozucu_buyruk),
    .regfile_wen_o(c2d_regfile_wen),
    .sabit_genisletici_secimi_o(c2d_imm_ext_sel),
    .amb_secim_o(c2a_alu_sel),
    .amb_fonksiyon_o(c2a_alu_fun)
    );
endmodule

top.v
module top (input clk_i,
            input rst_i);
    
    wire [31:0] buyruk;
    wire [31:0] buyruk_adres;
    
    kutu kutu1 (
    .clk_i(clk_i),
    .rst_i(rst_i),
    .buyruk_i(buyruk),
    .buyruk_adres_o(buyruk_adres)
    );
    
    bellek bellek1 (
    .clk_i(clk_i),
    .wen_i(1'b0),
    .adres_i(buyruk_adres),
    .veri_i(32'b0),
    .veri_o(buyruk)
    );
    
endmodule

waveform.vcd
$version Generated by VerilatedVcd $end
$timescale 1ps $end
 $scope module TOP $end
  $var wire 1 V clk_i $end
  $var wire 1 W rst_i $end
  $scope module top $end
   $var wire 1 V clk_i $end
   $var wire 1 W rst_i $end
   $var wire 32 C buyruk [31:0] $end
   $var wire 32 D buyruk_adres [31:0] $end
   $scope module bellek1 $end
    $var wire 1 V clk_i $end
    $var wire 1 Y wen_i $end
    $var wire 32 D adres_i [31:0] $end
    $var wire 32 Z veri_i [31:0] $end
    $var wire 32 C veri_o [31:0] $end
   $upscope $end
   $scope module kutu1 $end
    $var wire 1 V clk_i $end
    $var wire 1 W rst_i $end
    $var wire 32 C buyruk_i [31:0] $end
    $var wire 32 D buyruk_adres_o [31:0] $end
    $var wire 32 E getir_2_cozucu_buyruk [31:0] $end
    $var wire 1 F c2d_regfile_wen $end
    $var wire 3 G c2d_imm_ext_sel [2:0] $end
    $var wire 32 H w2d_result [31:0] $end
    $var wire 32 I d2a_reg_a [31:0] $end
    $var wire 32 X d2a_reg_b [31:0] $end
    $var wire 32 J d2a_imm_ext [31:0] $end
    $var wire 1 K c2a_alu_sel $end
    $var wire 4 L c2a_alu_fun [3:0] $end
    $var wire 32 H a2w_alu_out [31:0] $end
    $scope module amb1 $end
     $var wire 1 K amb_secim_i $end
     $var wire 4 L amb_fonksiyon_i [3:0] $end
     $var wire 32 I reg_a_i [31:0] $end
     $var wire 32 X reg_b_i [31:0] $end
     $var wire 32 J sabit_genisletici_i [31:0] $end
     $var wire 32 H amb_cikis_o [31:0] $end
     $var wire 32 I amb_a [31:0] $end
     $var wire 32 M amb_b [31:0] $end
    $upscope $end
    $scope module cozucu1 $end
     $var wire 1 V clk_i $end
     $var wire 1 F regfile_wen_i $end
     $var wire 3 G sabit_genisletici_secimi_i [2:0] $end
     $var wire 32 E buyruk_i [31:0] $end
     $var wire 32 H sonuc_i [31:0] $end
     $var wire 32 I reg_a_o [31:0] $end
     $var wire 32 X reg_b_o [31:0] $end
     $var wire 32 J sabit_genisletici_o [31:0] $end
     $var wire 32 # reg_dosyasi[0] [31:0] $end
     $var wire 32 $ reg_dosyasi[1] [31:0] $end
     $var wire 32 % reg_dosyasi[2] [31:0] $end
     $var wire 32 & reg_dosyasi[3] [31:0] $end
     $var wire 32 ' reg_dosyasi[4] [31:0] $end
     $var wire 32 ( reg_dosyasi[5] [31:0] $end
     $var wire 32 ) reg_dosyasi[6] [31:0] $end
     $var wire 32 * reg_dosyasi[7] [31:0] $end
     $var wire 32 + reg_dosyasi[8] [31:0] $end
     $var wire 32 , reg_dosyasi[9] [31:0] $end
     $var wire 32 - reg_dosyasi[10] [31:0] $end
     $var wire 32 . reg_dosyasi[11] [31:0] $end
     $var wire 32 / reg_dosyasi[12] [31:0] $end
     $var wire 32 0 reg_dosyasi[13] [31:0] $end
     $var wire 32 1 reg_dosyasi[14] [31:0] $end
     $var wire 32 2 reg_dosyasi[15] [31:0] $end
     $var wire 32 3 reg_dosyasi[16] [31:0] $end
     $var wire 32 4 reg_dosyasi[17] [31:0] $end
     $var wire 32 5 reg_dosyasi[18] [31:0] $end
     $var wire 32 6 reg_dosyasi[19] [31:0] $end
     $var wire 32 7 reg_dosyasi[20] [31:0] $end
     $var wire 32 8 reg_dosyasi[21] [31:0] $end
     $var wire 32 9 reg_dosyasi[22] [31:0] $end
     $var wire 32 : reg_dosyasi[23] [31:0] $end
     $var wire 32 ; reg_dosyasi[24] [31:0] $end
     $var wire 32 < reg_dosyasi[25] [31:0] $end
     $var wire 32 = reg_dosyasi[26] [31:0] $end
     $var wire 32 > reg_dosyasi[27] [31:0] $end
     $var wire 32 ? reg_dosyasi[28] [31:0] $end
     $var wire 32 @ reg_dosyasi[29] [31:0] $end
     $var wire 32 A reg_dosyasi[30] [31:0] $end
     $var wire 32 B reg_dosyasi[31] [31:0] $end
     $var wire 5 N reg_a_adres [4:0] $end
     $var wire 5 O reg_b_adres [4:0] $end
     $var wire 5 P hedef_reg_adres [4:0] $end
    $upscope $end
    $scope module gc_kaydedici1 $end
     $var wire 1 V clk_i $end
     $var wire 1 W rst_i $end
     $var wire 32 C buyruk_g_i [31:0] $end
     $var wire 32 E buyruk_c_o [31:0] $end
    $upscope $end
    $scope module geri_yazma1 $end
     $var wire 32 H amb_cikis_i [31:0] $end
     $var wire 32 H sonuc_o [31:0] $end
    $upscope $end
    $scope module getir1 $end
     $var wire 1 V clk_i $end
     $var wire 1 W rst_i $end
     $var wire 32 D pc_o [31:0] $end
    $upscope $end
    $scope module kontrolcu1 $end
     $var wire 32 E buyruk_i [31:0] $end
     $var wire 1 F regfile_wen_o $end
     $var wire 3 G sabit_genisletici_secimi_o [2:0] $end
     $var wire 1 K amb_secim_o $end
     $var wire 4 L amb_fonksiyon_o [3:0] $end
     $var wire 7 Q opcode [6:0] $end
     $var wire 3 R funct3 [2:0] $end
     $var wire 7 S funct7 [6:0] $end
     $var wire 2 T amb_cozucu [1:0] $end
     $var wire 7 U control_sinyalleri [6:0] $end
    $upscope $end
   $upscope $end
  $upscope $end
 $upscope $end
$enddefinitions $end


#0
b00000000000000000000000000000000 #
b00000000000000000000000000000000 $
b00000000000000000000000000000000 %
b00000000000000000000000000000000 &
b00000000000000000000000000000000 '
b00000000000000000000000000000000 (
b00000000000000000000000000000000 )
b00000000000000000000000000000000 *
b00000000000000000000000000000000 +
b00000000000000000000000000000000 ,
b00000000000000000000000000000000 -
b00000000000000000000000000000000 .
b00000000000000000000000000000000 /
b00000000000000000000000000000000 0
b00000000000000000000000000000000 1
b00000000000000000000000000000000 2
b00000000000000000000000000000000 3
b00000000000000000000000000000000 4
b00000000000000000000000000000000 5
b00000000000000000000000000000000 6
b00000000000000000000000000000000 7
b00000000000000000000000000000000 8
b00000000000000000000000000000000 9
b00000000000000000000000000000000 :
b00000000000000000000000000000000 ;
b00000000000000000000000000000000 <
b00000000000000000000000000000000 =
b00000000000000000000000000000000 >
b00000000000000000000000000000000 ?
b00000000000000000000000000000000 @
b00000000000000000000000000000000 A
b00000000000000000000000000000000 B
b00111110100000000000000010010011 C
b00000000000000000000000000000000 D
b00000000000000000000000000000000 E
0F
b000 G
b00000000000000000000000000000000 H
b00000000000000000000000000000000 I
b00000000000000000000000000000000 J
0K
b0000 L
b00000000000000000000000000000000 M
b00000 N
b00000 O
b00000 P
b0000000 Q
b000 R
b0000000 S
b00 T
b0000000 U
1V
0W
b00000000000000000000000000000000 X
0Y
b00000000000000000000000000000000 Z
#1
0V
#2
b01111101000000001000000100010011 C
b00000000000000000000000000000100 D
b00111110100000000000000010010011 E
1F
b00000000000000000000001111101000 H
b00000000000000000000001111101000 J
1K
b00000000000000000000001111101000 M
b01000 O
b00001 P
b0010011 Q
b0011111 S
b11 T
b1000111 U
1V
#3
0V
#4
b00000000000000000000001111101000 $
b11000001100000010000000110010011 C
b00000000000000000000000000001000 D
b01111101000000001000000100010011 E
b00000000000000000000101110111000 H
b00000000000000000000001111101000 I
b00000000000000000000011111010000 J
b00000000000000000000011111010000 M
b00001 N
b10000 O
b00010 P
b0111110 S
1V
#5
0V
#6
b00000000000000000000101110111000 %
b10000011000000011000001000010011 C
b00000000000000000000000000001100 D
b11000001100000010000000110010011 E
b00000000000000000000011111010000 H
b00000000000000000000101110111000 I
b11111111111111111111110000011000 J
b11111111111111111111110000011000 M
b00010 N
b11000 O
b00011 P
b1100000 S
1V
#7
0V
#8
b00000000000000000000011111010000 &
b00111110100000100000001010010011 C
b00000000000000000000000000010000 D
b10000011000000011000001000010011 E
b00000000000000000000000000000000 H
b00000000000000000000011111010000 I
b11111111111111111111100000110000 J
b11111111111111111111100000110000 M
b00011 N
b10000 O
b00100 P
b1000001 S
1V
#9
0V
#10
b00000000000000010000001100010111 C
b00000000000000000000000000010100 D
b00111110100000100000001010010011 E
b00000000000000000000001111101000 H
b00000000000000000000000000000000 I
b00000000000000000000001111101000 J
b00000000000000000000001111101000 M
b00100 N
b01000 O
b00101 P
b0011111 S
1V
#11
0V
#12
b00000000000000000000001111101000 (
b11111110110000110000001100010011 C
b00000000000000000000000000011000 D
b00000000000000010000001100010111 E
0F
b00000000000000000000101110111000 H
b00000000000000000000101110111000 I
b00000000000000000000000000000000 J
0K
b00000000000000000000000000000000 M
b00010 N
b00000 O
b00110 P
b0010111 Q
b0000000 S
b00 T
b0000000 U
1V
#13
0V
#14
b00000000010000110000001100010011 C
b00000000000000000000000000011100 D
b11111110110000110000001100010011 E
1F
b11111111111111111111111111101100 H
b00000000000000000000000000000000 I
b11111111111111111111111111101100 J
1K
b11111111111111111111111111101100 M
b00110 N
b01100 O
b0010011 Q
b1111111 S
b11 T
b1000111 U
1V
#15
0V
#16
b11111111111111111111111111101100 )
b00000000000000000000000000000000 C
b00000000000000000000000000100000 D
b00000000010000110000001100010011 E
b11111111111111111111111111110000 H
b11111111111111111111111111101100 I
b00000000000000000000000000000100 J
b00000000000000000000000000000100 M
b00100 O
b0000000 S
1V
#17
0V
#18
b11111111111111111111111111110000 )
b00000000000000000000000000100100 D
b00000000000000000000000000000000 E
0F
b00000000000000000000000000000000 H
b00000000000000000000000000000000 I
b00000000000000000000000000000000 J
0K
b00000000000000000000000000000000 M
b00000 N
b00000 O
b00000 P
b0000000 Q
b00 T
b0000000 U
1V
#19
0V
#20
b00000000000000000000000000101000 D
1V
#21
0V
#22
b00000000000000000000000000101100 D
1V
#23
0V
#24
b00000000000000000000000000110000 D
1V
#25
0V
#26
b00000000000000000000000000110100 D
1V
#27
0V
#28
b00000000000000000000000000111000 D
1V
